src/__init__.py
src/base/__init__.py
src/base/model.py
src/ensemble/__init__.py
src/ensemble/boosting.py
src/ensemble/forest.py
src/gaussian/__init__.py
src/gaussian/gaussian.py
src/linear/__init__.py
src/linear/lasso.py
src/linear/linear.py
src/linear/linreg.py
src/linear/logistic.py
src/linear/ridge.py
src/neighbors/__init__.py
src/neighbors/knn.py
src/tree/__init__.py
src/tree/tree.py
tulia-0.2.1.dist-info/LICENSE
tulia-0.2.1.dist-info/METADATA
tulia-0.2.1.dist-info/WHEEL
tulia-0.2.1.dist-info/top_level.txt
tulia-0.2.1.dist-info/RECORD
