Metadata-Version: 2.1
Name: tulia
Version: 0.2.1
Summary: numpy based machine learning package with sklearn-like API
Home-page: https://github.com/chuvalniy/tulia
Author: Valentin Belyaev
Author-email: chuvalik.work@gmail.com
License: MIT
Keywords: python,machine learning,from scratch,numpy,sklearn-like,random forest,tree,knn
Classifier: Development Status :: 2 - Pre-Alpha
Classifier: Intended Audience :: Developers
Classifier: Programming Language :: Python :: 3
Classifier: Operating System :: Unix
Classifier: Operating System :: MacOS :: MacOS X
Classifier: Operating System :: Microsoft :: Windows
License-File: LICENSE
Requires-Dist: numpy
Requires-Dist: pytest
